tree_sitter_tmux/__init__.pyi
tree_sitter_tmux/binding.c
tree_sitter_tmux/__init__.py
tree_sitter_tmux/py.typed
tree_sitter_tmux/_binding.abi3.so
tree_sitter_tmux-0.0.4.dist-info/RECORD
tree_sitter_tmux-0.0.4.dist-info/WHEEL
tree_sitter_tmux-0.0.4.dist-info/top_level.txt
tree_sitter_tmux-0.0.4.dist-info/METADATA
